paita/__about__.py
paita/__init__.py
paita/llm/__init__.py
paita/llm/callbacks.py
paita/llm/chat.py
paita/llm/chat_history.py
paita/llm/enums.py
paita/llm/message.py
paita/llm/models.py
paita/llm/services/__init__.py
paita/llm/services/bedrock.py
paita/llm/services/ollama.py
paita/llm/services/openai.py
paita/llm/services/service.py
paita/localization/__init__.py
paita/localization/labels.py
paita/rag/__init__.py
paita/rag/models.py
paita/rag/rag_manager.py
paita/tui/__init__.py
paita/tui/app.py
paita/tui/error_screen.py
paita/tui/factory.py
paita/tui/message_box.py
paita/tui/multi_line_input.py
paita/tui/settings_screen.py
paita/tui/wait_screen.py
paita/tui/styles/app.tcss
paita/tui/styles/error_screen.tcss
paita/tui/styles/message_box.tcss
paita/tui/styles/settings_screen.tcss
paita/tui/styles/wait_screen.tcss
paita/utils/__init__.py
paita/utils/config_dirs.py
paita/utils/file_utils.py
paita/utils/json_utils.py
paita/utils/logger.py
paita/utils/settings_manager.py
paita/utils/settings_model.py
paita/utils/string_utils.py
paita-0.1.13.dist-info/METADATA
paita-0.1.13.dist-info/WHEEL
paita-0.1.13.dist-info/entry_points.txt
paita-0.1.13.dist-info/licenses/LICENSE
paita-0.1.13.dist-info/RECORD
