Metadata-Version: 2.3
Name: paita
Version: 0.1.13
Summary: paita - Python AI Textual Assistant
Project-URL: Documentation, https://github.com/villekr/paita#readme
Project-URL: Issues, https://github.com/villekr/paita/issues
Project-URL: Source, https://github.com/villekr/paita
Author-email: Ville Kärkkäinen <ville.karkkainen@outlook.com>
License-Expression: MIT
License-File: LICENSE
Keywords: ai,aws,bedrock,chat,chatgpt,openai,python,textual
Classifier: Development Status :: 4 - Beta
Classifier: Programming Language :: Python
Classifier: Programming Language :: Python :: 3.8
Classifier: Programming Language :: Python :: 3.9
Classifier: Programming Language :: Python :: 3.10
Classifier: Programming Language :: Python :: 3.11
Classifier: Programming Language :: Python :: 3.12
Classifier: Programming Language :: Python :: Implementation :: CPython
Classifier: Programming Language :: Python :: Implementation :: PyPy
Requires-Python: >=3.8
Requires-Dist: aiofiles~=24.1.0
Requires-Dist: appdirs~=1.4.4
Requires-Dist: bs4~=0.0.2
Requires-Dist: cache3~=0.4.3
Requires-Dist: eval-type-backport~=0.2.0
Requires-Dist: langchain-aws~=0.1.17
Requires-Dist: langchain-chroma~=0.1.3
Requires-Dist: langchain-community~=0.2.14
Requires-Dist: langchain-core~=0.2.36
Requires-Dist: langchain-ollama~=0.1.2
Requires-Dist: langchain-openai~=0.1.23
Requires-Dist: langchain~=0.2.15
Requires-Dist: loguru~=0.7.2
Requires-Dist: lxml~=5.3.0
Requires-Dist: ollama~=0.3.2
Requires-Dist: pydantic~=2.8.2
Requires-Dist: pyperclip~=1.9.0
Requires-Dist: textual~=0.78.0
Requires-Dist: validators~=0.33.0
